tests/__init__.py
tests/conftest.py
tests/test_wiki_link.py
wikilink/__init__.py
wikilink/wiki_link.py
wikilink/db/__init__.py
wikilink/db/base.py
wikilink/db/connection.py
wikilink/db/link.py
wikilink/db/page.py
wikilink-0.3.0.post1.dist-info/LICENSE
wikilink-0.3.0.post1.dist-info/METADATA
wikilink-0.3.0.post1.dist-info/WHEEL
wikilink-0.3.0.post1.dist-info/top_level.txt
wikilink-0.3.0.post1.dist-info/RECORD
