Metadata-Version: 2.1
Name: wikilink
Version: 0.3.0.post1
Summary: A multiprocessing web-scraping application to scrape wiki pages and find minimum number of links between two given wiki pages.
Home-page: https://github.com/tranlyvu/wiki-link
Author: Tran Ly Vu
Author-email: vutransingapore@gmail.com
Maintainer: Tran Ly Vu <vutransingapore@gmail.com>
Maintainer-email: vutransingapore@gmail.com
License: Apache License 2.0
Project-URL: Source, https://github.com/tranlyvu/wiki-link
Project-URL: Tracker, https://github.com/tranlyvu/wiki-link/issues
Project-URL: Chat: Gitter, https://gitter.im/find-link/Lobby
Project-URL: CI: Travis, https://travis-ci.org/tranlyvu/wiki-link
Project-URL: Coverage: coveralls, https://coveralls.io/github/tranlyvu/wiki-link
Keywords: Web Scraping,Artificial Intelligence,Breadth First Search,Graph,Data Science,Web Extracting,Information Analysis
Platform: any
Classifier: Programming Language :: Python :: 3
Classifier: Programming Language :: Python :: 3.6
Classifier: Programming Language :: Python :: 3.7
Classifier: License :: OSI Approved :: Apache Software License 
Classifier: Operating System :: POSIX
Classifier: Operating System :: POSIX :: BSD
Classifier: Operating System :: POSIX :: Linux
Classifier: Operating System :: Unix
Classifier: Development Status :: 4 - Beta
Classifier: Natural Language :: English
Classifier: Environment :: Console
Classifier: Intended Audience :: Education
Classifier: Intended Audience :: End Users/Desktop
Classifier: Intended Audience :: Information Technology
Classifier: Intended Audience :: Science/Research
Classifier: Topic :: Scientific/Engineering :: Artificial Intelligence
Classifier: Topic :: Scientific/Engineering :: Information Analysis
Classifier: Topic :: Education
Classifier: Programming Language :: Python :: Implementation :: CPython
Classifier: Programming Language :: Python :: Implementation :: PyPy
Classifier: Framework :: Pytest
Classifier: Framework :: Flake8
Requires-Python: >=3.0, <4
Requires-Dist: beautifulsoup4 (>=4.7.1)
Requires-Dist: requests (>=2.21.0)
Requires-Dist: SQLAlchemy-Utils (>=0.33.11)
Requires-Dist: mysqlclient (>=1.4.2.post1)
